prince_calculator/__init__.py
prince_calculator-0.12.dist-info/LICENSE.txt
prince_calculator-0.12.dist-info/METADATA
prince_calculator-0.12.dist-info/WHEEL
prince_calculator-0.12.dist-info/top_level.txt
prince_calculator-0.12.dist-info/RECORD
